{ "compressionlevel":-1,
 "height":14,
 "infinite":false,
 "layers":[
        {
         "data":[0, 0, 0, 0, 0, 0, 0, 0, 0, 0, 0, 0, 0, 0, 0, 0, 0, 0, 0, 0, 0, 0, 0, 0, 0, 0, 0, 0, 0, 0, 0, 0, 0, 0, 0, 0, 0, 0, 0, 0, 0, 0, 0, 0, 0, 0, 0, 0, 0, 0, 0, 0, 0, 0, 0, 0, 0, 0, 0, 0, 0, 0, 0, 0, 0, 0, 0, 0, 0, 0, 0, 0, 0, 0, 0, 0, 0, 0, 0, 0, 0, 0, 0, 0, 0, 0, 0, 0, 0, 0, 0, 0, 0, 0, 0, 0, 0, 0, 0, 0, 0, 0, 0, 0, 0, 0, 0, 0, 0, 0, 0, 0, 0, 0, 0, 0, 0, 0, 0, 0, 0, 0, 0, 0, 0, 0, 0, 0, 0, 0, 0, 0, 0, 0, 0, 0, 0, 0, 0, 0, 0, 0, 0, 0, 0, 0, 0, 0, 0, 0, 0, 0, 0, 0, 0, 0, 0, 0, 0, 0, 0, 0, 0, 0, 0, 0, 0, 0, 0, 0, 0, 0, 0, 0, 0, 0, 0, 0, 0, 0, 0, 0, 0, 0, 0, 0, 0, 0, 0, 0, 0, 0, 0, 0, 0, 0, 0, 0, 0, 0, 0, 0, 0, 0, 0, 0, 0, 0, 0, 0, 0, 0, 0, 0, 0, 0, 0, 0, 0, 0, 0, 0, 0, 0, 0, 0, 0, 0, 0, 0, 0, 0, 0, 0, 0, 0, 0, 0, 0, 0, 0, 0, 0, 0, 0, 0, 0, 0, 0, 0, 0, 0, 0, 0, 0, 0, 0, 0, 0, 0, 0, 0, 0, 0, 0, 0, 0, 0, 0, 0, 0, 0, 0, 0, 0, 0, 0, 0, 0, 0, 0, 0, 0, 0, 0, 0, 0, 0, 0, 0, 0, 0, 0, 0, 0, 0, 0, 0, 0, 0, 0, 0, 0, 0, 0, 0, 0, 0, 0, 0, 0, 0, 0, 0, 0, 0, 0, 0, 0, 0, 0, 0, 0, 0, 0, 0, 0, 0, 0, 0, 0, 0, 0, 0, 0, 0, 0, 0, 0, 0, 0, 0, 0, 0, 0, 0, 0, 0, 0, 0, 0, 0, 0, 0, 0, 0, 0, 0, 0, 0, 0, 0, 0, 0, 0, 0, 0, 0, 0, 0, 0, 0, 0, 0, 0, 0, 0, 0, 0, 0, 0, 0, 0, 0, 0, 0, 0, 0, 0, 0, 0, 0, 0, 0, 0, 0, 0, 0, 0, 0, 0, 0, 0, 0, 0, 0, 0, 0, 0, 0, 0, 0, 0, 0, 0, 0, 0, 0, 0, 0, 0, 0, 0, 0, 0, 0, 0, 0, 0, 0, 0, 0, 0, 0, 0, 0, 0, 0, 0, 0, 0, 0, 0, 0, 0, 0, 0, 0, 0, 0, 0, 0, 0, 0, 0, 0, 0, 0, 0, 0, 0, 0, 0, 0, 0, 0, 0, 0, 0, 0, 0, 0, 0, 0, 0, 0, 0, 0, 0, 0, 0, 0, 0, 0, 0, 0, 0, 0, 0, 0, 0, 0, 0, 0, 0, 0, 0, 0, 0, 0, 0, 0, 0, 0, 0, 0, 0, 0, 0, 0, 0, 0, 0, 0, 0, 0, 0, 0, 0, 0, 0, 0, 0, 0, 0, 0, 0, 0, 0, 0, 0, 0, 0, 0, 0, 0, 0, 0, 0, 0, 0, 0, 0, 0, 0, 0, 0, 0, 0, 0, 0, 0, 0, 0, 0, 0, 0, 0, 0, 0, 0, 0, 0, 0, 0, 0, 0, 0, 0, 0, 0, 0, 0, 0, 0, 0, 0, 0, 0, 0, 0, 0, 0, 0, 0, 0, 0, 0, 0, 0, 0, 0, 0, 0, 0, 0, 0, 0, 0, 0, 0, 0, 0, 0, 0, 0, 0, 0, 0, 0, 0, 0, 0, 0, 0, 0, 0, 0, 0, 0, 0, 0, 0, 0, 0, 0, 0, 0, 0, 0, 0, 0, 0, 0, 0, 0, 0, 0, 0, 0, 0, 0, 0, 0, 0, 0, 0, 0, 0, 0, 0, 0, 0, 0, 0, 0, 0, 0, 0, 0, 0, 0, 0, 0, 0, 0, 0, 0, 0, 0, 0, 0, 0, 0, 0, 0, 0, 0, 0, 0, 0, 0, 0, 0, 0, 0, 0, 0, 0, 0, 0, 0, 0, 0, 0, 0, 0, 0, 0, 0, 0, 0, 0, 0, 0, 0, 0, 0, 0, 0, 0, 0, 0, 0, 0, 0, 0, 0, 0, 0, 0, 0, 0, 0, 0, 0, 0, 0, 0, 0, 0, 0, 0, 0, 0, 0, 0, 0, 0, 0, 0, 0, 0, 0, 0, 0, 0, 0, 0, 0, 0, 0, 0, 0, 0, 0, 0, 0, 0, 0, 0, 0, 0, 0, 0, 0, 0, 0, 0, 0, 0, 0, 0, 0, 0, 0, 0, 0, 0, 0, 0, 0, 0, 0, 0, 0, 0, 0, 0, 0, 0, 0, 0, 0, 0, 0, 0, 0, 0, 0, 0, 0, 0, 0, 0, 0, 11, 11, 11, 11, 11, 11, 0, 0, 0, 0, 0, 0, 0, 0, 0, 0, 0, 0, 0, 0, 0, 0, 0, 0, 0, 0, 0, 0, 0, 0, 0, 0, 0, 0, 0, 0, 0, 0, 0, 0, 0, 0, 0, 0, 0, 0, 0, 0, 0, 0, 0, 0, 0, 0, 0, 0, 0, 0, 0, 0, 0, 0, 0, 0, 0, 0, 0, 0, 0, 0, 0, 0, 0, 0, 0, 0, 0, 0, 0, 0, 0, 0, 0, 0, 0, 0, 0, 0, 0, 0, 0, 0, 0, 0, 0, 0, 0, 0, 0, 0, 0, 0, 0, 0, 0, 0, 0, 0, 0, 0, 0, 0, 0, 0, 0, 0, 0, 0, 0, 0, 0, 0, 0, 0, 0, 0, 0, 0, 0, 0, 0, 0, 0, 0, 0, 0, 0, 0, 0, 0, 0, 0, 0, 0, 0, 0, 0, 0, 0, 0, 0, 0, 0, 0, 0, 0, 0, 0, 0, 0, 0, 0, 0, 0, 0, 0, 0, 0, 0, 0, 0, 0, 7, 0, 0, 0, 0, 0, 0, 0, 0, 0, 0, 7, 0, 0, 0, 0, 0, 0, 0, 0, 0, 0, 0, 0, 0, 0, 0, 0, 0, 0, 0, 0, 0, 0, 0, 0, 0, 0, 0, 0, 0, 0, 0, 0, 0, 0, 0, 0, 0, 0, 0, 0, 0, 0, 0, 0, 0, 0, 0, 0, 0, 0, 11, 11, 11, 11, 11, 11, 14, 14, 11, 11, 11, 11, 11, 11, 11, 16, 16, 16, 7, 7, 7, 7, 7, 7, 7, 7, 7, 7, 7, 7, 0, 0, 0, 0, 0, 0, 0, 0, 0, 0, 0, 0, 0, 0, 0, 0, 0, 0, 0, 0, 0, 0, 0, 0, 0, 0, 0, 0, 0, 0, 0, 0, 0, 0, 0, 0, 0, 0, 0, 0, 0, 0, 0, 0, 0, 0, 0, 0, 0, 0],
         "height":14,
         "id":1,
         "name":"platforms",
         "opacity":1,
         "type":"tilelayer",
         "visible":true,
         "width":80,
         "x":0,
         "y":0
        }, 
        {
         "draworder":"topdown",
         "id":7,
         "name":"enemies2",
         "objects":[
                {
                 "gid":2,
                 "height":70,
                 "id":63,
                 "name":"",
                 "rotation":0,
                 "type":"",
                 "visible":true,
                 "width":70,
                 "x":1814.33,
                 "y":901.667
                }, 
                {
                 "gid":2,
                 "height":70,
                 "id":64,
                 "name":"",
                 "rotation":0,
                 "type":"",
                 "visible":true,
                 "width":70,
                 "x":1542.33,
                 "y":901.667
                }],
         "opacity":1,
         "type":"objectgroup",
         "visible":true,
         "x":0,
         "y":0
        }, 
        {
         "draworder":"topdown",
         "id":5,
         "name":"enemies1",
         "objects":[
                {
                 "gid":1,
                 "height":70,
                 "id":65,
                 "name":"",
                 "rotation":0,
                 "type":"",
                 "visible":true,
                 "width":70,
                 "x":1398.33,
                 "y":901.667
                }, 
                {
                 "gid":1,
                 "height":70,
                 "id":66,
                 "name":"",
                 "rotation":0,
                 "type":"",
                 "visible":true,
                 "width":70,
                 "x":1681,
                 "y":901.667
                }],
         "opacity":1,
         "type":"objectgroup",
         "visible":true,
         "x":0,
         "y":0
        }, 
        {
         "draworder":"topdown",
         "id":10,
         "name":"info",
         "objects":[
                {
                 "gid":3,
                 "height":70,
                 "id":67,
                 "name":"",
                 "rotation":0,
                 "type":"",
                 "visible":true,
                 "width":70,
                 "x":911.667,
                 "y":912.333
                }, 
                {
                 "gid":3,
                 "height":70,
                 "id":71,
                 "name":"",
                 "rotation":0,
                 "type":"",
                 "visible":true,
                 "width":70,
                 "x":562.333,
                 "y":696.333
                }],
         "opacity":1,
         "type":"objectgroup",
         "visible":true,
         "x":0,
         "y":0
        }, 
        {
         "draworder":"topdown",
         "id":9,
         "name":"flag",
         "objects":[
                {
                 "gid":18,
                 "height":70,
                 "id":57,
                 "name":"",
                 "rotation":0,
                 "type":"",
                 "visible":true,
                 "width":70,
                 "x":702.333,
                 "y":909.667
                }],
         "opacity":1,
         "type":"objectgroup",
         "visible":true,
         "x":0,
         "y":0
        }, 
        {
         "draworder":"topdown",
         "id":8,
         "name":"coins",
         "objects":[
                {
                 "gid":9,
                 "height":70,
                 "id":59,
                 "name":"",
                 "rotation":0,
                 "type":"",
                 "visible":true,
                 "width":70,
                 "x":419.667,
                 "y":692.333
                }, 
                {
                 "gid":9,
                 "height":70,
                 "id":60,
                 "name":"",
                 "rotation":0,
                 "type":"",
                 "visible":true,
                 "width":70,
                 "x":346.333,
                 "y":912.333
                }, 
                {
                 "gid":32,
                 "height":70,
                 "id":74,
                 "name":"",
                 "rotation":0,
                 "type":"",
                 "visible":true,
                 "width":70,
                 "x":770.333333333333,
                 "y":699
                }],
         "opacity":1,
         "type":"objectgroup",
         "visible":true,
         "x":0,
         "y":0
        }, 
        {
         "draworder":"topdown",
         "id":6,
         "name":"diamonds",
         "objects":[
                {
                 "gid":10,
                 "height":70,
                 "id":68,
                 "name":"",
                 "rotation":0,
                 "type":"",
                 "visible":true,
                 "width":70,
                 "x":213,
                 "y":908.333
                }, 
                {
                 "gid":10,
                 "height":70,
                 "id":69,
                 "name":"",
                 "rotation":0,
                 "type":"",
                 "visible":true,
                 "width":70,
                 "x":282.333,
                 "y":907
                }, 
                {
                 "gid":33,
                 "height":70,
                 "id":72,
                 "name":"",
                 "rotation":0,
                 "type":"",
                 "visible":true,
                 "width":70,
                 "x":487.666666666667,
                 "y":699
                }, 
                {
                 "gid":57,
                 "height":70,
                 "id":73,
                 "name":"",
                 "rotation":0,
                 "type":"",
                 "visible":true,
                 "width":70,
                 "x":697,
                 "y":699
                }],
         "opacity":1,
         "type":"objectgroup",
         "visible":true,
         "x":0,
         "y":0
        }],
 "nextlayerid":11,
 "nextobjectid":75,
 "orientation":"orthogonal",
 "renderorder":"right-down",
 "tiledversion":"1.7.2",
 "tileheight":70,
 "tilesets":[
        {
         "columns":1,
         "firstgid":1,
         "image":"..\/img\/tiles.png",
         "imageheight":1610,
         "imagewidth":70,
         "margin":0,
         "name":"tiles",
         "spacing":0,
         "tilecount":23,
         "tileheight":70,
         "tilewidth":70,
         "transparentcolor":"#ff00ff"
        }, 
        {
         "columns":1,
         "firstgid":24,
         "image":"..\/img\/tilesAsia.png",
         "imageheight":1610,
         "imagewidth":70,
         "margin":0,
         "name":"tilesAsia",
         "spacing":0,
         "tilecount":23,
         "tileheight":70,
         "tilewidth":70,
         "transparentcolor":"#ff00ff"
        }, 
        {
         "columns":1,
         "firstgid":47,
         "image":"..\/img\/tilesMania.png",
         "imageheight":1470,
         "imagewidth":70,
         "margin":0,
         "name":"tilesMania",
         "spacing":0,
         "tilecount":21,
         "tileheight":70,
         "tilewidth":70,
         "transparentcolor":"#ff00ff"
        }],
 "tilewidth":70,
 "type":"map",
 "version":"1.6",
 "width":80
}